odoo/addons/test_queue_job/README.rst
odoo/addons/test_queue_job/__init__.py
odoo/addons/test_queue_job/__manifest__.py
odoo/addons/test_queue_job/data/queue_job_channel_data.xml
odoo/addons/test_queue_job/data/queue_job_function_data.xml
odoo/addons/test_queue_job/i18n/fr.po
odoo/addons/test_queue_job/i18n/test_queue_job.pot
odoo/addons/test_queue_job/i18n/zh_CN.po
odoo/addons/test_queue_job/models/__init__.py
odoo/addons/test_queue_job/models/test_models.py
odoo/addons/test_queue_job/security/ir.model.access.csv
odoo/addons/test_queue_job/static/description/icon.png
odoo/addons/test_queue_job/tests/__init__.py
odoo/addons/test_queue_job/tests/common.py
odoo/addons/test_queue_job/tests/test_autovacuum.py
odoo/addons/test_queue_job/tests/test_job.py
odoo/addons/test_queue_job/tests/test_job_auto_delay.py
odoo/addons/test_queue_job/tests/test_job_channels.py
odoo/addons/test_queue_job/tests/test_json_field.py
odoo/addons/test_queue_job/tests/test_related_actions.py
odoo13_addon_test_queue_job-13.0.2.5.0.dist-info/METADATA
odoo13_addon_test_queue_job-13.0.2.5.0.dist-info/WHEEL
odoo13_addon_test_queue_job-13.0.2.5.0.dist-info/top_level.txt
odoo13_addon_test_queue_job-13.0.2.5.0.dist-info/RECORD
