Metadata-Version: 2.1
Name: odoo13-addon-test-queue-job
Version: 13.0.2.5.0
Summary: Queue Job Tests
Home-page: https://github.com/OCA/queue
Author: Camptocamp,Odoo Community Association (OCA)
Author-email: support@odoo-community.org
License: LGPL-3
Platform: UNKNOWN
Classifier: Programming Language :: Python
Classifier: Framework :: Odoo
Classifier: Framework :: Odoo :: 13.0
Classifier: License :: OSI Approved :: GNU Lesser General Public License v3 (LGPLv3)
Requires-Python: >=3.5
Requires-Dist: odoo13-addon-queue-job
Requires-Dist: odoo (<13.1dev,>=13.0a)
